dmtopython/__init__.py
dmtopython/dm.py
dmtopython/dm_ai.py
dmtopython/dm_asm.py
dmtopython/dm_bg.py
dmtopython/dm_dmg.py
dmtopython/dm_faq.py
dmtopython/dm_file.py
dmtopython/dm_find.py
dmtopython/dm_foobar.py
dmtopython/dm_keyboard.py
dmtopython/dm_memory.py
dmtopython/dm_mouse.py
dmtopython/dm_ocr.py
dmtopython/dm_system.py
dmtopython/dm_window.py
dmtopython-0.1.3.dist-info/LICENSE
dmtopython-0.1.3.dist-info/METADATA
dmtopython-0.1.3.dist-info/WHEEL
dmtopython-0.1.3.dist-info/top_level.txt
dmtopython-0.1.3.dist-info/RECORD
